{
  "fr_FR": {
    "translation": {
      "view_options": "View options",
      "intro": "Intro",
      "stories": "Stories",
      "archive": "Archive",
      "about": "About",
      "terms_of_use": "Terms of use",
      "contact_us": "Contact us",
      "close_options": "Close options",
      "documentType_audio": "Audio",
      "documentType_pdf": "Documents",
      "documentType_video": "Videos",
      "documentType_image": "Photographs",
      "orderBy_most_recent": "From the most recent",
      "orderBy_least_recent": "From the least recent",
      "orderBy_by_type": "By type",
      "include_no_dates": "Include elements without dates",
      "grid_size": "Grid size",
      "sort_items": "Sort items",
      "search": "Search",
      "filter_by_type": "Filter by type",
      "filter_by_year": "Filter by year",
      "story-video": "video",
      "story-interactive-video": "video",
      "story-audio": "audio",
      "story-map": "interactive map",
      "story-graphic-novel": "graphic novel",
      "story-article": "article",
      "explore": "explore",
      "watch": "watch",
      "listen": "listen",
      "start": "start",
      "creator": "creator",
      "provenance": "provenance",
      "copyright": "copyright",
      "listen-to-podcast": "Listen To the podcast on your favourite podcast player:",
      "download-file": "Download file",
      "remixing_industrial": "Remixing Industrial Pasts in the Digital Age",
      "take_me_there": "Take me there",
      "interactiveVideoTip": "Move the white circle to interact with the interactive documentary.",
      "graphicNovelTip": "Scroll horizontally to read the graphic novel or use the arrows",
      "skipIntro": "Skip Intro",
      "scrollDown": "Scroll Down",
      "go_deeper": "Go deeper",
      "open":"Open",
      "research_by": "Research By",
      "education": "Education"
    }
  },
  "en_GB": {
    "translation": {
      "view_options": "View options",
      "intro": "Intro",
      "stories": "Stories",
      "archive": "Archive",
      "about": "About",
      "terms_of_use": "Terms of use",
      "contact_us": "Contact us",
      "close_options": "Close options",
      "documentType_audio": "Audio",
      "documentType_pdf": "Documents",
      "documentType_video": "Videos",
      "documentType_image": "Photographs",
      "orderBy_most_recent": "From the most recent",
      "orderBy_least_recent": "From the least recent",
      "orderBy_by_type": "By type",
      "include_no_dates": "Include elements without dates",
      "grid_size": "Grid size",
      "sort_items": "Sort items",
      "search": "Search",
      "filter_by_type": "Filter by type",
      "filter_by_year": "Filter by year",
      "story-video": "video",
      "story-interactive-video": "video",
      "story-audio": "audio",
      "story-map": "interactive map",
      "story-graphic-novel": "graphic novel",
      "story-article": "article",
      "explore": "explore",
      "watch": "watch",
      "listen": "listen",
      "start": "start",
      "creator": "creator",
      "provenance": "provenance",
      "copyright": "copyright",
      "listen-to-podcast": "Listen To the podcast on your favourite podcast player:",
      "download-file": "Download file",
      "remixing_industrial": "Remixing Industrial Pasts in the Digital Age",
      "take_me_there": "Take me there",
      "interactiveVideoTip": "Move the white circle to interact with the interactive documentary.",
      "graphicNovelTip": "Scroll horizontally to read the graphic novel or use the arrows",
      "skipIntro": "Skip Intro",
      "scrollDown": "Scroll Down",
      "go_deeper": "Go deeper",
      "open": "Open",
      "research_by": "Research By",
      "education": "Education"
    }
  },
  "de_DE": {
    "translation": {
      "view_options": "View options",
      "intro": "Intro",
      "stories": "Stories",
      "archive": "Archive",
      "about": "About",
      "terms_of_use": "Terms of use",
      "contact_us": "Contact us",
      "close_options": "Close options",
      "documentType_audio": "Audio",
      "documentType_pdf": "Documents",
      "documentType_video": "Videos",
      "documentType_image": "Photographs",
      "orderBy_most_recent": "From the most recent",
      "orderBy_least_recent": "From the least recent",
      "orderBy_by_type": "By type",
      "include_no_dates": "Include elements without dates",
      "grid_size": "Grid size",
      "sort_items": "Sort items",
      "search": "Search",
      "filter_by_type": "Filter by type",
      "filter_by_year": "Filter by year",
      "story-video": "video",
      "story-interactive-video": "video",
      "story-audio": "audio",
      "story-map": "interactive map",
      "story-graphic-novel": "graphic novel",
      "story-article": "article",
      "explore": "explore",
      "watch": "watch",
      "listen": "listen",
      "start": "start",
      "creator": "creator",
      "provenance": "provenance",
      "copyright": "copyright",
      "listen-to-podcast": "Listen To the podcast on your favourite podcast player:",
      "download-file": "Download file",
      "remixing_industrial": "Remixing Industrial Pasts in the Digital Age",
      "take_me_there": "Take me there",
      "interactiveVideoTip": "Move the white circle to interact with the interactive documentary.",
      "graphicNovelTip": "Scroll horizontally to read the graphic novel or use the arrows",
      "skipIntro": "Skip Intro",
      "scrollDown": "Scroll Down",
      "go_deeper": "Go deeper",
      "open": "Open",
      "research_by": "Research By",
      "education": "Education"
    }
  }
}